MANIFEST.in
README.md
README.rst
flask_bitjws.py
setup.py
flask_bitjws.egg-info/PKG-INFO
flask_bitjws.egg-info/SOURCES.txt
flask_bitjws.egg-info/dependency_links.txt
flask_bitjws.egg-info/requires.txt
flask_bitjws.egg-info/top_level.txt
test/test_init.py
test/test_mimetype.py
test/test_request.py