Metadata-Version: 1.1
Name: flask-bitjws
Version: 0.1.1.5
Summary: A Flask extension for bitjws authentication.
Home-page: https://github.com/deginner/flask-bitjws
Author: deginner
Author-email: support@deginner.com
License: MIT
Platform: UNKNOWN
Classifier: License :: OSI Approved :: MIT License
Classifier: Programming Language :: Python :: 2
Classifier: Topic :: Software Development :: Libraries
